{
  "records": [
    {
      "timestamp": "2025-10-12T06:00:00+02:00",
      "date": "2025-10-12",
      "hour_local": 6,
      "server": "Netherworld",
      "player": "1Klas",
      "player_key": "1klas",
      "kills_hour": 2375,
      "kills_cum_day": 2375,
      "rank_today": 11
    },
    {
      "timestamp": "2025-10-12T07:00:00+02:00",
      "date": "2025-10-12",
      "hour_local": 7,
      "server": "Netherworld",
      "player": "1Klas",
      "player_key": "1klas",
      "kills_hour": 3004,
      "kills_cum_day": 5379,
      "rank_today": 6
    },
    {
      "timestamp": "2025-10-12T08:00:00+02:00",
      "date": "2025-10-12",
      "hour_local": 8,
      "server": "Netherworld",
      "player": "1Klas",
      "player_key": "1klas",
      "kills_hour": 3241,
      "kills_cum_day": 8620,
      "rank_today": 2
    },
    {
      "timestamp": "2025-10-12T09:00:00+02:00",
      "date": "2025-10-12",
      "hour_local": 9,
      "server": "Netherworld",
      "player": "1Klas",
      "player_key": "1klas",
      "kills_hour": 871,
      "kills_cum_day": 9491,
      "rank_today": 2
    },
    {
      "timestamp": "2025-10-12T10:00:00+02:00",
      "date": "2025-10-12",
      "hour_local": 10,
      "server": "Netherworld",
      "player": "1Klas",
      "player_key": "1klas",
      "kills_hour": 1140,
      "kills_cum_day": 10631,
      "rank_today": 4
    },
    {
      "timestamp": "2025-10-12T00:00:00+02:00",
      "date": "2025-10-12",
      "hour_local": 0,
      "server": "Netherworld",
      "player": "AETHER",
      "player_key": "aether",
      "kills_hour": 261,
      "kills_cum_day": 261,
      "rank_today": 11
    },
    {
      "timestamp": "2025-10-12T01:00:00+02:00",
      "date": "2025-10-12",
      "hour_local": 1,
      "server": "Netherworld",
      "player": "AETHER",
      "player_key": "aether",
      "kills_hour": 530,
      "kills_cum_day": 791,
      "rank_today": 13
    },
    {
      "timestamp": "2025-10-12T05:00:00+02:00",
      "date": "2025-10-12",
      "hour_local": 5,
      "server": "Netherworld",
      "player": "AETHER",
      "player_key": "aether",
      "kills_hour": 1163,
      "kills_cum_day": 1954,
      "rank_today": 11
    },
    {
      "timestamp": "2025-10-12T06:00:00+02:00",
      "date": "2025-10-12",
      "hour_local": 6,
      "server": "Netherworld",
      "player": "AETHER",
      "player_key": "aether",
      "kills_hour": 98,
      "kills_cum_day": 2052,
      "rank_today": 12
    },
    {
      "timestamp": "2025-10-12T07:00:00+02:00",
      "date": "2025-10-12",
      "hour_local": 7,
      "server": "Netherworld",
      "player": "AETHER",
      "player_key": "aether",
      "kills_hour": 0,
      "kills_cum_day": 2052,
      "rank_today": 12
    },
    {
      "timestamp": "2025-10-12T08:00:00+02:00",
      "date": "2025-10-12",
      "hour_local": 8,
      "server": "Netherworld",
      "player": "AETHER",
      "player_key": "aether",
      "kills_hour": 0,
      "kills_cum_day": 2052,
      "rank_today": 13
    },
    {
      "timestamp": "2025-10-12T09:00:00+02:00",
      "date": "2025-10-12",
      "hour_local": 9,
      "server": "Netherworld",
      "player": "AETHER",
      "player_key": "aether",
      "kills_hour": 0,
      "kills_cum_day": 2052,
      "rank_today": 13
    },
    {
      "timestamp": "2025-10-12T10:00:00+02:00",
      "date": "2025-10-12",
      "hour_local": 10,
      "server": "Netherworld",
      "player": "AETHER",
      "player_key": "aether",
      "kills_hour": 0,
      "kills_cum_day": 2052,
      "rank_today": 17
    },
    {
      "timestamp": "2025-10-12T00:00:00+02:00",
      "date": "2025-10-12",
      "hour_local": 0,
      "server": "Netherworld",
      "player": "Albert",
      "player_key": "albert",
      "kills_hour": 1381,
      "kills_cum_day": 1381,
      "rank_today": 4
    },
    {
      "timestamp": "2025-10-12T01:00:00+02:00",
      "date": "2025-10-12",
      "hour_local": 1,
      "server": "Netherworld",
      "player": "Albert",
      "player_key": "albert",
      "kills_hour": 1473,
      "kills_cum_day": 2854,
      "rank_today": 7
    },
    {
      "timestamp": "2025-10-12T05:00:00+02:00",
      "date": "2025-10-12",
      "hour_local": 5,
      "server": "Netherworld",
      "player": "Albert",
      "player_key": "albert",
      "kills_hour": 5,
      "kills_cum_day": 2859,
      "rank_today": 10
    },
    {
      "timestamp": "2025-10-12T06:00:00+02:00",
      "date": "2025-10-12",
      "hour_local": 6,
      "server": "Netherworld",
      "player": "Albert",
      "player_key": "albert",
      "kills_hour": 1,
      "kills_cum_day": 2860,
      "rank_today": 10
    },
    {
      "timestamp": "2025-10-12T07:00:00+02:00",
      "date": "2025-10-12",
      "hour_local": 7,
      "server": "Netherworld",
      "player": "Albert",
      "player_key": "albert",
      "kills_hour": 0,
      "kills_cum_day": 2860,
      "rank_today": 11
    },
    {
      "timestamp": "2025-10-12T08:00:00+02:00",
      "date": "2025-10-12",
      "hour_local": 8,
      "server": "Netherworld",
      "player": "Albert",
      "player_key": "albert",
      "kills_hour": 2,
      "kills_cum_day": 2862,
      "rank_today": 12
    },
    {
      "timestamp": "2025-10-12T09:00:00+02:00",
      "date": "2025-10-12",
      "hour_local": 9,
      "server": "Netherworld",
      "player": "Albert",
      "player_key": "albert",
      "kills_hour": 1,
      "kills_cum_day": 2863,
      "rank_today": 12
    },
    {
      "timestamp": "2025-10-12T10:00:00+02:00",
      "date": "2025-10-12",
      "hour_local": 10,
      "server": "Netherworld",
      "player": "Albert",
      "player_key": "albert",
      "kills_hour": 1,
      "kills_cum_day": 2864,
      "rank_today": 15
    },
    {
      "timestamp": "2025-10-12T10:00:00+02:00",
      "date": "2025-10-12",
      "hour_local": 10,
      "server": "Netherworld",
      "player": "Alibaba",
      "player_key": "alibaba",
      "kills_hour": 101,
      "kills_cum_day": 101,
      "rank_today": 40
    },
    {
      "timestamp": "2025-10-12T08:00:00+02:00",
      "date": "2025-10-12",
      "hour_local": 8,
      "server": "Netherworld",
      "player": "Amogus",
      "player_key": "amogus",
      "kills_hour": 503,
      "kills_cum_day": 503,
      "rank_today": 28
    },
    {
      "timestamp": "2025-10-12T09:00:00+02:00",
      "date": "2025-10-12",
      "hour_local": 9,
      "server": "Netherworld",
      "player": "Amogus",
      "player_key": "amogus",
      "kills_hour": 721,
      "kills_cum_day": 1224,
      "rank_today": 19
    },
    {
      "timestamp": "2025-10-12T10:00:00+02:00",
      "date": "2025-10-12",
      "hour_local": 10,
      "server": "Netherworld",
      "player": "Amogus",
      "player_key": "amogus",
      "kills_hour": 1114,
      "kills_cum_day": 2338,
      "rank_today": 16
    },
    {
      "timestamp": "2025-10-12T00:00:00+02:00",
      "date": "2025-10-12",
      "hour_local": 0,
      "server": "Netherworld",
      "player": "AntsInThePants",
      "player_key": "antsinthepants",
      "kills_hour": 2296,
      "kills_cum_day": 2296,
      "rank_today": 1
    },
    {
      "timestamp": "2025-10-12T01:00:00+02:00",
      "date": "2025-10-12",
      "hour_local": 1,
      "server": "Netherworld",
      "player": "AntsInThePants",
      "player_key": "antsinthepants",
      "kills_hour": 1178,
      "kills_cum_day": 3474,
      "rank_today": 3
    },
    {
      "timestamp": "2025-10-12T05:00:00+02:00",
      "date": "2025-10-12",
      "hour_local": 5,
      "server": "Netherworld",
      "player": "AntsInThePants",
      "player_key": "antsinthepants",
      "kills_hour": 0,
      "kills_cum_day": 3474,
      "rank_today": 7
    },
    {
      "timestamp": "2025-10-12T06:00:00+02:00",
      "date": "2025-10-12",
      "hour_local": 6,
      "server": "Netherworld",
      "player": "AntsInThePants",
      "player_key": "antsinthepants",
      "kills_hour": 0,
      "kills_cum_day": 3474,
      "rank_today": 7
    },
    {
      "timestamp": "2025-10-12T07:00:00+02:00",
      "date": "2025-10-12",
      "hour_local": 7,
      "server": "Netherworld",
      "player": "AntsInThePants",
      "player_key": "antsinthepants",
      "kills_hour": 0,
      "kills_cum_day": 3474,
      "rank_today": 8
    },
    {
      "timestamp": "2025-10-12T08:00:00+02:00",
      "date": "2025-10-12",
      "hour_local": 8,
      "server": "Netherworld",
      "player": "AntsInThePants",
      "player_key": "antsinthepants",
      "kills_hour": 0,
      "kills_cum_day": 3474,
      "rank_today": 9
    },
    {
      "timestamp": "2025-10-12T09:00:00+02:00",
      "date": "2025-10-12",
      "hour_local": 9,
      "server": "Netherworld",
      "player": "AntsInThePants",
      "player_key": "antsinthepants",
      "kills_hour": 0,
      "kills_cum_day": 3474,
      "rank_today": 9
    },
    {
      "timestamp": "2025-10-12T10:00:00+02:00",
      "date": "2025-10-12",
      "hour_local": 10,
      "server": "Netherworld",
      "player": "AntsInThePants",
      "player_key": "antsinthepants",
      "kills_hour": 0,
      "kills_cum_day": 3474,
      "rank_today": 12
    },
    {
      "timestamp": "2025-10-12T05:00:00+02:00",
      "date": "2025-10-12",
      "hour_local": 5,
      "server": "Netherworld",
      "player": "Arishem",
      "player_key": "arishem",
      "kills_hour": 55,
      "kills_cum_day": 55,
      "rank_today": 29
    },
    {
      "timestamp": "2025-10-12T06:00:00+02:00",
      "date": "2025-10-12",
      "hour_local": 6,
      "server": "Netherworld",
      "player": "Arishem",
      "player_key": "arishem",
      "kills_hour": 873,
      "kills_cum_day": 928,
      "rank_today": 21
    },
    {
      "timestamp": "2025-10-12T07:00:00+02:00",
      "date": "2025-10-12",
      "hour_local": 7,
      "server": "Netherworld",
      "player": "Arishem",
      "player_key": "arishem",
      "kills_hour": 0,
      "kills_cum_day": 928,
      "rank_today": 21
    },
    {
      "timestamp": "2025-10-12T08:00:00+02:00",
      "date": "2025-10-12",
      "hour_local": 8,
      "server": "Netherworld",
      "player": "Arishem",
      "player_key": "arishem",
      "kills_hour": 0,
      "kills_cum_day": 928,
      "rank_today": 23
    },
    {
      "timestamp": "2025-10-12T09:00:00+02:00",
      "date": "2025-10-12",
      "hour_local": 9,
      "server": "Netherworld",
      "player": "Arishem",
      "player_key": "arishem",
      "kills_hour": 0,
      "kills_cum_day": 928,
      "rank_today": 25
    },
    {
      "timestamp": "2025-10-12T10:00:00+02:00",
      "date": "2025-10-12",
      "hour_local": 10,
      "server": "Netherworld",
      "player": "Arishem",
      "player_key": "arishem",
      "kills_hour": 0,
      "kills_cum_day": 928,
      "rank_today": 30
    },
    {
      "timestamp": "2025-10-12T05:00:00+02:00",
      "date": "2025-10-12",
      "hour_local": 5,
      "server": "Netherworld",
      "player": "Aynne",
      "player_key": "aynne",
      "kills_hour": 355,
      "kills_cum_day": 355,
      "rank_today": 24
    },
    {
      "timestamp": "2025-10-12T06:00:00+02:00",
      "date": "2025-10-12",
      "hour_local": 6,
      "server": "Netherworld",
      "player": "Aynne",
      "player_key": "aynne",
      "kills_hour": 0,
      "kills_cum_day": 355,
      "rank_today": 26
    },
    {
      "timestamp": "2025-10-12T07:00:00+02:00",
      "date": "2025-10-12",
      "hour_local": 7,
      "server": "Netherworld",
      "player": "Aynne",
      "player_key": "aynne",
      "kills_hour": 0,
      "kills_cum_day": 355,
      "rank_today": 27
    },
    {
      "timestamp": "2025-10-12T08:00:00+02:00",
      "date": "2025-10-12",
      "hour_local": 8,
      "server": "Netherworld",
      "player": "Aynne",
      "player_key": "aynne",
      "kills_hour": 0,
      "kills_cum_day": 355,
      "rank_today": 29
    },
    {
      "timestamp": "2025-10-12T09:00:00+02:00",
      "date": "2025-10-12",
      "hour_local": 9,
      "server": "Netherworld",
      "player": "Aynne",
      "player_key": "aynne",
      "kills_hour": 0,
      "kills_cum_day": 355,
      "rank_today": 33
    },
    {
      "timestamp": "2025-10-12T10:00:00+02:00",
      "date": "2025-10-12",
      "hour_local": 10,
      "server": "Netherworld",
      "player": "Aynne",
      "player_key": "aynne",
      "kills_hour": 0,
      "kills_cum_day": 355,
      "rank_today": 36
    },
    {
      "timestamp": "2025-10-12T07:00:00+02:00",
      "date": "2025-10-12",
      "hour_local": 7,
      "server": "Netherworld",
      "player": "Beef",
      "player_key": "beef",
      "kills_hour": 9,
      "kills_cum_day": 9,
      "rank_today": 33
    },
    {
      "timestamp": "2025-10-12T08:00:00+02:00",
      "date": "2025-10-12",
      "hour_local": 8,
      "server": "Netherworld",
      "player": "Beef",
      "player_key": "beef",
      "kills_hour": 4,
      "kills_cum_day": 13,
      "rank_today": 38
    },
    {
      "timestamp": "2025-10-12T09:00:00+02:00",
      "date": "2025-10-12",
      "hour_local": 9,
      "server": "Netherworld",
      "player": "Beef",
      "player_key": "beef",
      "kills_hour": 0,
      "kills_cum_day": 13,
      "rank_today": 40
    },
    {
      "timestamp": "2025-10-12T10:00:00+02:00",
      "date": "2025-10-12",
      "hour_local": 10,
      "server": "Netherworld",
      "player": "Beef",
      "player_key": "beef",
      "kills_hour": 0,
      "kills_cum_day": 13,
      "rank_today": 45
    },
    {
      "timestamp": "2025-10-12T00:00:00+02:00",
      "date": "2025-10-12",
      "hour_local": 0,
      "server": "Netherworld",
      "player": "Beeru",
      "player_key": "beeru",
      "kills_hour": 6,
      "kills_cum_day": 6,
      "rank_today": 16
    },
    {
      "timestamp": "2025-10-12T01:00:00+02:00",
      "date": "2025-10-12",
      "hour_local": 1,
      "server": "Netherworld",
      "player": "Beeru",
      "player_key": "beeru",
      "kills_hour": 123,
      "kills_cum_day": 129,
      "rank_today": 17
    },
    {
      "timestamp": "2025-10-12T05:00:00+02:00",
      "date": "2025-10-12",
      "hour_local": 5,
      "server": "Netherworld",
      "player": "Beeru",
      "player_key": "beeru",
      "kills_hour": 659,
      "kills_cum_day": 788,
      "rank_today": 20
    },
    {
      "timestamp": "2025-10-12T06:00:00+02:00",
      "date": "2025-10-12",
      "hour_local": 6,
      "server": "Netherworld",
      "player": "Beeru",
      "player_key": "beeru",
      "kills_hour": 0,
      "kills_cum_day": 788,
      "rank_today": 23
    },
    {
      "timestamp": "2025-10-12T07:00:00+02:00",
      "date": "2025-10-12",
      "hour_local": 7,
      "server": "Netherworld",
      "player": "Beeru",
      "player_key": "beeru",
      "kills_hour": 0,
      "kills_cum_day": 788,
      "rank_today": 23
    },
    {
      "timestamp": "2025-10-12T08:00:00+02:00",
      "date": "2025-10-12",
      "hour_local": 8,
      "server": "Netherworld",
      "player": "Beeru",
      "player_key": "beeru",
      "kills_hour": 0,
      "kills_cum_day": 788,
      "rank_today": 25
    },
    {
      "timestamp": "2025-10-12T09:00:00+02:00",
      "date": "2025-10-12",
      "hour_local": 9,
      "server": "Netherworld",
      "player": "Beeru",
      "player_key": "beeru",
      "kills_hour": 0,
      "kills_cum_day": 788,
      "rank_today": 29
    },
    {
      "timestamp": "2025-10-12T10:00:00+02:00",
      "date": "2025-10-12",
      "hour_local": 10,
      "server": "Netherworld",
      "player": "Beeru",
      "player_key": "beeru",
      "kills_hour": 0,
      "kills_cum_day": 788,
      "rank_today": 33
    },
    {
      "timestamp": "2025-10-12T00:00:00+02:00",
      "date": "2025-10-12",
      "hour_local": 0,
      "server": "Netherworld",
      "player": "Bersey",
      "player_key": "bersey",
      "kills_hour": 218,
      "kills_cum_day": 218,
      "rank_today": 12
    },
    {
      "timestamp": "2025-10-12T01:00:00+02:00",
      "date": "2025-10-12",
      "hour_local": 1,
      "server": "Netherworld",
      "player": "Bersey",
      "player_key": "bersey",
      "kills_hour": 1304,
      "kills_cum_day": 1522,
      "rank_today": 9
    },
    {
      "timestamp": "2025-10-12T05:00:00+02:00",
      "date": "2025-10-12",
      "hour_local": 5,
      "server": "Netherworld",
      "player": "Bersey",
      "player_key": "bersey",
      "kills_hour": 0,
      "kills_cum_day": 1522,
      "rank_today": 13
    },
    {
      "timestamp": "2025-10-12T06:00:00+02:00",
      "date": "2025-10-12",
      "hour_local": 6,
      "server": "Netherworld",
      "player": "Bersey",
      "player_key": "bersey",
      "kills_hour": 0,
      "kills_cum_day": 1522,
      "rank_today": 14
    },
    {
      "timestamp": "2025-10-12T07:00:00+02:00",
      "date": "2025-10-12",
      "hour_local": 7,
      "server": "Netherworld",
      "player": "Bersey",
      "player_key": "bersey",
      "kills_hour": 0,
      "kills_cum_day": 1522,
      "rank_today": 14
    },
    {
      "timestamp": "2025-10-12T08:00:00+02:00",
      "date": "2025-10-12",
      "hour_local": 8,
      "server": "Netherworld",
      "player": "Bersey",
      "player_key": "bersey",
      "kills_hour": 0,
      "kills_cum_day": 1522,
      "rank_today": 15
    },
    {
      "timestamp": "2025-10-12T09:00:00+02:00",
      "date": "2025-10-12",
      "hour_local": 9,
      "server": "Netherworld",
      "player": "Bersey",
      "player_key": "bersey",
      "kills_hour": 0,
      "kills_cum_day": 1522,
      "rank_today": 16
    },
    {
      "timestamp": "2025-10-12T10:00:00+02:00",
      "date": "2025-10-12",
      "hour_local": 10,
      "server": "Netherworld",
      "player": "Bersey",
      "player_key": "bersey",
      "kills_hour": 0,
      "kills_cum_day": 1522,
      "rank_today": 21
    },
    {
      "timestamp": "2025-10-12T00:00:00+02:00",
      "date": "2025-10-12",
      "hour_local": 0,
      "server": "Netherworld",
      "player": "BrainTrain",
      "player_key": "braintrain",
      "kills_hour": 22,
      "kills_cum_day": 22,
      "rank_today": 15
    },
    {
      "timestamp": "2025-10-12T01:00:00+02:00",
      "date": "2025-10-12",
      "hour_local": 1,
      "server": "Netherworld",
      "player": "BrainTrain",
      "player_key": "braintrain",
      "kills_hour": 0,
      "kills_cum_day": 22,
      "rank_today": 19
    },
    {
      "timestamp": "2025-10-12T05:00:00+02:00",
      "date": "2025-10-12",
      "hour_local": 5,
      "server": "Netherworld",
      "player": "BrainTrain",
      "player_key": "braintrain",
      "kills_hour": 0,
      "kills_cum_day": 22,
      "rank_today": 31
    },
    {
      "timestamp": "2025-10-12T06:00:00+02:00",
      "date": "2025-10-12",
      "hour_local": 6,
      "server": "Netherworld",
      "player": "BrainTrain",
      "player_key": "braintrain",
      "kills_hour": 0,
      "kills_cum_day": 22,
      "rank_today": 32
    },
    {
      "timestamp": "2025-10-12T07:00:00+02:00",
      "date": "2025-10-12",
      "hour_local": 7,
      "server": "Netherworld",
      "player": "BrainTrain",
      "player_key": "braintrain",
      "kills_hour": 0,
      "kills_cum_day": 22,
      "rank_today": 32
    },
    {
      "timestamp": "2025-10-12T08:00:00+02:00",
      "date": "2025-10-12",
      "hour_local": 8,
      "server": "Netherworld",
      "player": "BrainTrain",
      "player_key": "braintrain",
      "kills_hour": 0,
      "kills_cum_day": 22,
      "rank_today": 37
    },
    {
      "timestamp": "2025-10-12T09:00:00+02:00",
      "date": "2025-10-12",
      "hour_local": 9,
      "server": "Netherworld",
      "player": "BrainTrain",
      "player_key": "braintrain",
      "kills_hour": 0,
      "kills_cum_day": 22,
      "rank_today": 39
    },
    {
      "timestamp": "2025-10-12T10:00:00+02:00",
      "date": "2025-10-12",
      "hour_local": 10,
      "server": "Netherworld",
      "player": "BrainTrain",
      "player_key": "braintrain",
      "kills_hour": 0,
      "kills_cum_day": 22,
      "rank_today": 43
    },
    {
      "timestamp": "2025-10-12T09:00:00+02:00",
      "date": "2025-10-12",
      "hour_local": 9,
      "server": "Netherworld",
      "player": "Bricks",
      "player_key": "bricks",
      "kills_hour": 187,
      "kills_cum_day": 187,
      "rank_today": 35
    },
    {
      "timestamp": "2025-10-12T10:00:00+02:00",
      "date": "2025-10-12",
      "hour_local": 10,
      "server": "Netherworld",
      "player": "Bricks",
      "player_key": "bricks",
      "kills_hour": 1820,
      "kills_cum_day": 2007,
      "rank_today": 18
    },
    {
      "timestamp": "2025-10-12T05:00:00+02:00",
      "date": "2025-10-12",
      "hour_local": 5,
      "server": "Netherworld",
      "player": "Chedda",
      "player_key": "chedda",
      "kills_hour": 4719,
      "kills_cum_day": 4719,
      "rank_today": 6
    },
    {
      "timestamp": "2025-10-12T06:00:00+02:00",
      "date": "2025-10-12",
      "hour_local": 6,
      "server": "Netherworld",
      "player": "Chedda",
      "player_key": "chedda",
      "kills_hour": 421,
      "kills_cum_day": 5140,
      "rank_today": 6
    },
    {
      "timestamp": "2025-10-12T07:00:00+02:00",
      "date": "2025-10-12",
      "hour_local": 7,
      "server": "Netherworld",
      "player": "Chedda",
      "player_key": "chedda",
      "kills_hour": 138,
      "kills_cum_day": 5278,
      "rank_today": 7
    },
    {
      "timestamp": "2025-10-12T08:00:00+02:00",
      "date": "2025-10-12",
      "hour_local": 8,
      "server": "Netherworld",
      "player": "Chedda",
      "player_key": "chedda",
      "kills_hour": 274,
      "kills_cum_day": 5552,
      "rank_today": 7
    },
    {
      "timestamp": "2025-10-12T09:00:00+02:00",
      "date": "2025-10-12",
      "hour_local": 9,
      "server": "Netherworld",
      "player": "Chedda",
      "player_key": "chedda",
      "kills_hour": 609,
      "kills_cum_day": 6161,
      "rank_today": 7
    },
    {
      "timestamp": "2025-10-12T10:00:00+02:00",
      "date": "2025-10-12",
      "hour_local": 10,
      "server": "Netherworld",
      "player": "Chedda",
      "player_key": "chedda",
      "kills_hour": 1093,
      "kills_cum_day": 7254,
      "rank_today": 7
    },
    {
      "timestamp": "2025-10-12T10:00:00+02:00",
      "date": "2025-10-12",
      "hour_local": 10,
      "server": "Netherworld",
      "player": "ConvenientStore",
      "player_key": "convenientstore",
      "kills_hour": 4,
      "kills_cum_day": 4,
      "rank_today": 46
    },
    {
      "timestamp": "2025-10-12T05:00:00+02:00",
      "date": "2025-10-12",
      "hour_local": 5,
      "server": "Netherworld",
      "player": "Dragneel",
      "player_key": "dragneel",
      "kills_hour": 598,
      "kills_cum_day": 598,
      "rank_today": 21
    },
    {
      "timestamp": "2025-10-12T06:00:00+02:00",
      "date": "2025-10-12",
      "hour_local": 6,
      "server": "Netherworld",
      "player": "Dragneel",
      "player_key": "dragneel",
      "kills_hour": 218,
      "kills_cum_day": 816,
      "rank_today": 22
    },
    {
      "timestamp": "2025-10-12T07:00:00+02:00",
      "date": "2025-10-12",
      "hour_local": 7,
      "server": "Netherworld",
      "player": "Dragneel",
      "player_key": "dragneel",
      "kills_hour": 0,
      "kills_cum_day": 816,
      "rank_today": 22
    },
    {
      "timestamp": "2025-10-12T08:00:00+02:00",
      "date": "2025-10-12",
      "hour_local": 8,
      "server": "Netherworld",
      "player": "Dragneel",
      "player_key": "dragneel",
      "kills_hour": 0,
      "kills_cum_day": 816,
      "rank_today": 24
    },
    {
      "timestamp": "2025-10-12T09:00:00+02:00",
      "date": "2025-10-12",
      "hour_local": 9,
      "server": "Netherworld",
      "player": "Dragneel",
      "player_key": "dragneel",
      "kills_hour": 0,
      "kills_cum_day": 816,
      "rank_today": 27
    },
    {
      "timestamp": "2025-10-12T10:00:00+02:00",
      "date": "2025-10-12",
      "hour_local": 10,
      "server": "Netherworld",
      "player": "Dragneel",
      "player_key": "dragneel",
      "kills_hour": 0,
      "kills_cum_day": 816,
      "rank_today": 31
    },
    {
      "timestamp": "2025-10-12T08:00:00+02:00",
      "date": "2025-10-12",
      "hour_local": 8,
      "server": "Netherworld",
      "player": "Endorphin",
      "player_key": "endorphin",
      "kills_hour": 5034,
      "kills_cum_day": 5034,
      "rank_today": 8
    },
    {
      "timestamp": "2025-10-12T09:00:00+02:00",
      "date": "2025-10-12",
      "hour_local": 9,
      "server": "Netherworld",
      "player": "Endorphin",
      "player_key": "endorphin",
      "kills_hour": 3523,
      "kills_cum_day": 8557,
      "rank_today": 3
    },
    {
      "timestamp": "2025-10-12T10:00:00+02:00",
      "date": "2025-10-12",
      "hour_local": 10,
      "server": "Netherworld",
      "player": "Endorphin",
      "player_key": "endorphin",
      "kills_hour": 5861,
      "kills_cum_day": 14418,
      "rank_today": 2
    },
    {
      "timestamp": "2025-10-12T05:00:00+02:00",
      "date": "2025-10-12",
      "hour_local": 5,
      "server": "Netherworld",
      "player": "Erdem",
      "player_key": "erdem",
      "kills_hour": 529,
      "kills_cum_day": 529,
      "rank_today": 23
    },
    {
      "timestamp": "2025-10-12T06:00:00+02:00",
      "date": "2025-10-12",
      "hour_local": 6,
      "server": "Netherworld",
      "player": "Erdem",
      "player_key": "erdem",
      "kills_hour": 0,
      "kills_cum_day": 529,
      "rank_today": 25
    },
    {
      "timestamp": "2025-10-12T07:00:00+02:00",
      "date": "2025-10-12",
      "hour_local": 7,
      "server": "Netherworld",
      "player": "Erdem",
      "player_key": "erdem",
      "kills_hour": 112,
      "kills_cum_day": 641,
      "rank_today": 25
    },
    {
      "timestamp": "2025-10-12T08:00:00+02:00",
      "date": "2025-10-12",
      "hour_local": 8,
      "server": "Netherworld",
      "player": "Erdem",
      "player_key": "erdem",
      "kills_hour": 0,
      "kills_cum_day": 641,
      "rank_today": 26
    },
    {
      "timestamp": "2025-10-12T09:00:00+02:00",
      "date": "2025-10-12",
      "hour_local": 9,
      "server": "Netherworld",
      "player": "Erdem",
      "player_key": "erdem",
      "kills_hour": 0,
      "kills_cum_day": 641,
      "rank_today": 30
    },
    {
      "timestamp": "2025-10-12T10:00:00+02:00",
      "date": "2025-10-12",
      "hour_local": 10,
      "server": "Netherworld",
      "player": "Erdem",
      "player_key": "erdem",
      "kills_hour": 0,
      "kills_cum_day": 641,
      "rank_today": 34
    },
    {
      "timestamp": "2025-10-12T08:00:00+02:00",
      "date": "2025-10-12",
      "hour_local": 8,
      "server": "Netherworld",
      "player": "Falkenauge",
      "player_key": "falkenauge",
      "kills_hour": 226,
      "kills_cum_day": 226,
      "rank_today": 32
    },
    {
      "timestamp": "2025-10-12T09:00:00+02:00",
      "date": "2025-10-12",
      "hour_local": 9,
      "server": "Netherworld",
      "player": "Falkenauge",
      "player_key": "falkenauge",
      "kills_hour": 898,
      "kills_cum_day": 1124,
      "rank_today": 20
    },
    {
      "timestamp": "2025-10-12T10:00:00+02:00",
      "date": "2025-10-12",
      "hour_local": 10,
      "server": "Netherworld",
      "player": "Falkenauge",
      "player_key": "falkenauge",
      "kills_hour": 0,
      "kills_cum_day": 1124,
      "rank_today": 25
    },
    {
      "timestamp": "2025-10-12T00:00:00+02:00",
      "date": "2025-10-12",
      "hour_local": 0,
      "server": "Netherworld",
      "player": "FarmerJoe",
      "player_key": "farmerjoe",
      "kills_hour": 1593,
      "kills_cum_day": 1593,
      "rank_today": 3
    },
    {
      "timestamp": "2025-10-12T01:00:00+02:00",
      "date": "2025-10-12",
      "hour_local": 1,
      "server": "Netherworld",
      "player": "FarmerJoe",
      "player_key": "farmerjoe",
      "kills_hour": 1569,
      "kills_cum_day": 3162,
      "rank_today": 5
    },
    {
      "timestamp": "2025-10-12T05:00:00+02:00",
      "date": "2025-10-12",
      "hour_local": 5,
      "server": "Netherworld",
      "player": "FarmerJoe",
      "player_key": "farmerjoe",
      "kills_hour": 0,
      "kills_cum_day": 3162,
      "rank_today": 8
    },
    {
      "timestamp": "2025-10-12T06:00:00+02:00",
      "date": "2025-10-12",
      "hour_local": 6,
      "server": "Netherworld",
      "player": "FarmerJoe",
      "player_key": "farmerjoe",
      "kills_hour": 0,
      "kills_cum_day": 3162,
      "rank_today": 8
    },
    {
      "timestamp": "2025-10-12T07:00:00+02:00",
      "date": "2025-10-12",
      "hour_local": 7,
      "server": "Netherworld",
      "player": "FarmerJoe",
      "player_key": "farmerjoe",
      "kills_hour": 0,
      "kills_cum_day": 3162,
      "rank_today": 9
    },
    {
      "timestamp": "2025-10-12T08:00:00+02:00",
      "date": "2025-10-12",
      "hour_local": 8,
      "server": "Netherworld",
      "player": "FarmerJoe",
      "player_key": "farmerjoe",
      "kills_hour": 0,
      "kills_cum_day": 3162,
      "rank_today": 10
    },
    {
      "timestamp": "2025-10-12T09:00:00+02:00",
      "date": "2025-10-12",
      "hour_local": 9,
      "server": "Netherworld",
      "player": "FarmerJoe",
      "player_key": "farmerjoe",
      "kills_hour": 0,
      "kills_cum_day": 3162,
      "rank_today": 10
    },
    {
      "timestamp": "2025-10-12T10:00:00+02:00",
      "date": "2025-10-12",
      "hour_local": 10,
      "server": "Netherworld",
      "player": "FarmerJoe",
      "player_key": "farmerjoe",
      "kills_hour": 0,
      "kills_cum_day": 3162,
      "rank_today": 13
    },
    {
      "timestamp": "2025-10-12T10:00:00+02:00",
      "date": "2025-10-12",
      "hour_local": 10,
      "server": "Netherworld",
      "player": "Gabranth",
      "player_key": "gabranth",
      "kills_hour": 20,
      "kills_cum_day": 20,
      "rank_today": 44
    },
    {
      "timestamp": "2025-10-12T00:00:00+02:00",
      "date": "2025-10-12",
      "hour_local": 0,
      "server": "Netherworld",
      "player": "GandalfTheGrey",
      "player_key": "gandalfthegrey",
      "kills_hour": 1000,
      "kills_cum_day": 1000,
      "rank_today": 6
    },
    {
      "timestamp": "2025-10-12T01:00:00+02:00",
      "date": "2025-10-12",
      "hour_local": 1,
      "server": "Netherworld",
      "player": "GandalfTheGrey",
      "player_key": "gandalfthegrey",
      "kills_hour": 2230,
      "kills_cum_day": 3230,
      "rank_today": 4
    },
    {
      "timestamp": "2025-10-12T05:00:00+02:00",
      "date": "2025-10-12",
      "hour_local": 5,
      "server": "Netherworld",
      "player": "GandalfTheGrey",
      "player_key": "gandalfthegrey",
      "kills_hour": 5018,
      "kills_cum_day": 8248,
      "rank_today": 3
    },
    {
      "timestamp": "2025-10-12T06:00:00+02:00",
      "date": "2025-10-12",
      "hour_local": 6,
      "server": "Netherworld",
      "player": "GandalfTheGrey",
      "player_key": "gandalfthegrey",
      "kills_hour": 0,
      "kills_cum_day": 8248,
      "rank_today": 3
    },
    {
      "timestamp": "2025-10-12T07:00:00+02:00",
      "date": "2025-10-12",
      "hour_local": 7,
      "server": "Netherworld",
      "player": "GandalfTheGrey",
      "player_key": "gandalfthegrey",
      "kills_hour": 0,
      "kills_cum_day": 8248,
      "rank_today": 3
    },
    {
      "timestamp": "2025-10-12T08:00:00+02:00",
      "date": "2025-10-12",
      "hour_local": 8,
      "server": "Netherworld",
      "player": "GandalfTheGrey",
      "player_key": "gandalfthegrey",
      "kills_hour": 0,
      "kills_cum_day": 8248,
      "rank_today": 4
    },
    {
      "timestamp": "2025-10-12T09:00:00+02:00",
      "date": "2025-10-12",
      "hour_local": 9,
      "server": "Netherworld",
      "player": "GandalfTheGrey",
      "player_key": "gandalfthegrey",
      "kills_hour": 0,
      "kills_cum_day": 8248,
      "rank_today": 5
    },
    {
      "timestamp": "2025-10-12T10:00:00+02:00",
      "date": "2025-10-12",
      "hour_local": 10,
      "server": "Netherworld",
      "player": "GandalfTheGrey",
      "player_key": "gandalfthegrey",
      "kills_hour": 2577,
      "kills_cum_day": 10825,
      "rank_today": 3
    },
    {
      "timestamp": "2025-10-12T05:00:00+02:00",
      "date": "2025-10-12",
      "hour_local": 5,
      "server": "Netherworld",
      "player": "Griever",
      "player_key": "griever",
      "kills_hour": 535,
      "kills_cum_day": 535,
      "rank_today": 22
    },
    {
      "timestamp": "2025-10-12T06:00:00+02:00",
      "date": "2025-10-12",
      "hour_local": 6,
      "server": "Netherworld",
      "player": "Griever",
      "player_key": "griever",
      "kills_hour": 0,
      "kills_cum_day": 535,
      "rank_today": 24
    },
    {
      "timestamp": "2025-10-12T07:00:00+02:00",
      "date": "2025-10-12",
      "hour_local": 7,
      "server": "Netherworld",
      "player": "Griever",
      "player_key": "griever",
      "kills_hour": 0,
      "kills_cum_day": 535,
      "rank_today": 26
    },
    {
      "timestamp": "2025-10-12T08:00:00+02:00",
      "date": "2025-10-12",
      "hour_local": 8,
      "server": "Netherworld",
      "player": "Griever",
      "player_key": "griever",
      "kills_hour": 0,
      "kills_cum_day": 535,
      "rank_today": 27
    },
    {
      "timestamp": "2025-10-12T09:00:00+02:00",
      "date": "2025-10-12",
      "hour_local": 9,
      "server": "Netherworld",
      "player": "Griever",
      "player_key": "griever",
      "kills_hour": 0,
      "kills_cum_day": 535,
      "rank_today": 31
    },
    {
      "timestamp": "2025-10-12T10:00:00+02:00",
      "date": "2025-10-12",
      "hour_local": 10,
      "server": "Netherworld",
      "player": "Griever",
      "player_key": "griever",
      "kills_hour": 0,
      "kills_cum_day": 535,
      "rank_today": 35
    },
    {
      "timestamp": "2025-10-12T05:00:00+02:00",
      "date": "2025-10-12",
      "hour_local": 5,
      "server": "Netherworld",
      "player": "Igris",
      "player_key": "igris",
      "kills_hour": 1366,
      "kills_cum_day": 1366,
      "rank_today": 14
    },
    {
      "timestamp": "2025-10-12T06:00:00+02:00",
      "date": "2025-10-12",
      "hour_local": 6,
      "server": "Netherworld",
      "player": "Igris",
      "player_key": "igris",
      "kills_hour": 0,
      "kills_cum_day": 1366,
      "rank_today": 15
    },
    {
      "timestamp": "2025-10-12T07:00:00+02:00",
      "date": "2025-10-12",
      "hour_local": 7,
      "server": "Netherworld",
      "player": "Igris",
      "player_key": "igris",
      "kills_hour": 0,
      "kills_cum_day": 1366,
      "rank_today": 15
    },
    {
      "timestamp": "2025-10-12T08:00:00+02:00",
      "date": "2025-10-12",
      "hour_local": 8,
      "server": "Netherworld",
      "player": "Igris",
      "player_key": "igris",
      "kills_hour": 0,
      "kills_cum_day": 1366,
      "rank_today": 17
    },
    {
      "timestamp": "2025-10-12T09:00:00+02:00",
      "date": "2025-10-12",
      "hour_local": 9,
      "server": "Netherworld",
      "player": "Igris",
      "player_key": "igris",
      "kills_hour": 0,
      "kills_cum_day": 1366,
      "rank_today": 17
    },
    {
      "timestamp": "2025-10-12T10:00:00+02:00",
      "date": "2025-10-12",
      "hour_local": 10,
      "server": "Netherworld",
      "player": "Igris",
      "player_key": "igris",
      "kills_hour": 0,
      "kills_cum_day": 1366,
      "rank_today": 23
    },
    {
      "timestamp": "2025-10-12T05:00:00+02:00",
      "date": "2025-10-12",
      "hour_local": 5,
      "server": "Netherworld",
      "player": "IrkedFarmer",
      "player_key": "irkedfarmer",
      "kills_hour": 1772,
      "kills_cum_day": 1772,
      "rank_today": 12
    },
    {
      "timestamp": "2025-10-12T06:00:00+02:00",
      "date": "2025-10-12",
      "hour_local": 6,
      "server": "Netherworld",
      "player": "IrkedFarmer",
      "player_key": "irkedfarmer",
      "kills_hour": 0,
      "kills_cum_day": 1772,
      "rank_today": 13
    },
    {
      "timestamp": "2025-10-12T07:00:00+02:00",
      "date": "2025-10-12",
      "hour_local": 7,
      "server": "Netherworld",
      "player": "IrkedFarmer",
      "player_key": "irkedfarmer",
      "kills_hour": 0,
      "kills_cum_day": 1772,
      "rank_today": 13
    },
    {
      "timestamp": "2025-10-12T08:00:00+02:00",
      "date": "2025-10-12",
      "hour_local": 8,
      "server": "Netherworld",
      "player": "IrkedFarmer",
      "player_key": "irkedfarmer",
      "kills_hour": 0,
      "kills_cum_day": 1772,
      "rank_today": 14
    },
    {
      "timestamp": "2025-10-12T09:00:00+02:00",
      "date": "2025-10-12",
      "hour_local": 9,
      "server": "Netherworld",
      "player": "IrkedFarmer",
      "player_key": "irkedfarmer",
      "kills_hour": 0,
      "kills_cum_day": 1772,
      "rank_today": 14
    },
    {
      "timestamp": "2025-10-12T10:00:00+02:00",
      "date": "2025-10-12",
      "hour_local": 10,
      "server": "Netherworld",
      "player": "IrkedFarmer",
      "player_key": "irkedfarmer",
      "kills_hour": 0,
      "kills_cum_day": 1772,
      "rank_today": 20
    },
    {
      "timestamp": "2025-10-12T05:00:00+02:00",
      "date": "2025-10-12",
      "hour_local": 5,
      "server": "Netherworld",
      "player": "IrkedIntrovert",
      "player_key": "irkedintrovert",
      "kills_hour": 3089,
      "kills_cum_day": 3089,
      "rank_today": 9
    },
    {
      "timestamp": "2025-10-12T06:00:00+02:00",
      "date": "2025-10-12",
      "hour_local": 6,
      "server": "Netherworld",
      "player": "IrkedIntrovert",
      "player_key": "irkedintrovert",
      "kills_hour": 0,
      "kills_cum_day": 3089,
      "rank_today": 9
    },
    {
      "timestamp": "2025-10-12T07:00:00+02:00",
      "date": "2025-10-12",
      "hour_local": 7,
      "server": "Netherworld",
      "player": "IrkedIntrovert",
      "player_key": "irkedintrovert",
      "kills_hour": 0,
      "kills_cum_day": 3089,
      "rank_today": 10
    },
    {
      "timestamp": "2025-10-12T08:00:00+02:00",
      "date": "2025-10-12",
      "hour_local": 8,
      "server": "Netherworld",
      "player": "IrkedIntrovert",
      "player_key": "irkedintrovert",
      "kills_hour": 0,
      "kills_cum_day": 3089,
      "rank_today": 11
    },
    {
      "timestamp": "2025-10-12T09:00:00+02:00",
      "date": "2025-10-12",
      "hour_local": 9,
      "server": "Netherworld",
      "player": "IrkedIntrovert",
      "player_key": "irkedintrovert",
      "kills_hour": 0,
      "kills_cum_day": 3089,
      "rank_today": 11
    },
    {
      "timestamp": "2025-10-12T10:00:00+02:00",
      "date": "2025-10-12",
      "hour_local": 10,
      "server": "Netherworld",
      "player": "IrkedIntrovert",
      "player_key": "irkedintrovert",
      "kills_hour": 0,
      "kills_cum_day": 3089,
      "rank_today": 14
    },
    {
      "timestamp": "2025-10-12T08:00:00+02:00",
      "date": "2025-10-12",
      "hour_local": 8,
      "server": "Netherworld",
      "player": "Josef",
      "player_key": "josef",
      "kills_hour": 315,
      "kills_cum_day": 315,
      "rank_today": 30
    },
    {
      "timestamp": "2025-10-12T09:00:00+02:00",
      "date": "2025-10-12",
      "hour_local": 9,
      "server": "Netherworld",
      "player": "Josef",
      "player_key": "josef",
      "kills_hour": 477,
      "kills_cum_day": 792,
      "rank_today": 28
    },
    {
      "timestamp": "2025-10-12T10:00:00+02:00",
      "date": "2025-10-12",
      "hour_local": 10,
      "server": "Netherworld",
      "player": "Josef",
      "player_key": "josef",
      "kills_hour": 0,
      "kills_cum_day": 792,
      "rank_today": 32
    },
    {
      "timestamp": "2025-10-12T01:00:00+02:00",
      "date": "2025-10-12",
      "hour_local": 1,
      "server": "Netherworld",
      "player": "Kweekmachine",
      "player_key": "kweekmachine",
      "kills_hour": 1017,
      "kills_cum_day": 1017,
      "rank_today": 12
    },
    {
      "timestamp": "2025-10-12T05:00:00+02:00",
      "date": "2025-10-12",
      "hour_local": 5,
      "server": "Netherworld",
      "player": "Kweekmachine",
      "player_key": "kweekmachine",
      "kills_hour": 13,
      "kills_cum_day": 1030,
      "rank_today": 18
    },
    {
      "timestamp": "2025-10-12T06:00:00+02:00",
      "date": "2025-10-12",
      "hour_local": 6,
      "server": "Netherworld",
      "player": "Kweekmachine",
      "player_key": "kweekmachine",
      "kills_hour": 0,
      "kills_cum_day": 1030,
      "rank_today": 19
    },
    {
      "timestamp": "2025-10-12T07:00:00+02:00",
      "date": "2025-10-12",
      "hour_local": 7,
      "server": "Netherworld",
      "player": "Kweekmachine",
      "player_key": "kweekmachine",
      "kills_hour": 0,
      "kills_cum_day": 1030,
      "rank_today": 19
    },
    {
      "timestamp": "2025-10-12T08:00:00+02:00",
      "date": "2025-10-12",
      "hour_local": 8,
      "server": "Netherworld",
      "player": "Kweekmachine",
      "player_key": "kweekmachine",
      "kills_hour": 0,
      "kills_cum_day": 1030,
      "rank_today": 20
    },
    {
      "timestamp": "2025-10-12T09:00:00+02:00",
      "date": "2025-10-12",
      "hour_local": 9,
      "server": "Netherworld",
      "player": "Kweekmachine",
      "player_key": "kweekmachine",
      "kills_hour": 0,
      "kills_cum_day": 1030,
      "rank_today": 22
    },
    {
      "timestamp": "2025-10-12T10:00:00+02:00",
      "date": "2025-10-12",
      "hour_local": 10,
      "server": "Netherworld",
      "player": "Kweekmachine",
      "player_key": "kweekmachine",
      "kills_hour": 0,
      "kills_cum_day": 1030,
      "rank_today": 27
    },
    {
      "timestamp": "2025-10-12T01:00:00+02:00",
      "date": "2025-10-12",
      "hour_local": 1,
      "server": "Netherworld",
      "player": "Litus",
      "player_key": "litus",
      "kills_hour": 454,
      "kills_cum_day": 454,
      "rank_today": 15
    },
    {
      "timestamp": "2025-10-12T05:00:00+02:00",
      "date": "2025-10-12",
      "hour_local": 5,
      "server": "Netherworld",
      "player": "Litus",
      "player_key": "litus",
      "kills_hour": 610,
      "kills_cum_day": 1064,
      "rank_today": 17
    },
    {
      "timestamp": "2025-10-12T06:00:00+02:00",
      "date": "2025-10-12",
      "hour_local": 6,
      "server": "Netherworld",
      "player": "Litus",
      "player_key": "litus",
      "kills_hour": 0,
      "kills_cum_day": 1064,
      "rank_today": 18
    },
    {
      "timestamp": "2025-10-12T07:00:00+02:00",
      "date": "2025-10-12",
      "hour_local": 7,
      "server": "Netherworld",
      "player": "Litus",
      "player_key": "litus",
      "kills_hour": 0,
      "kills_cum_day": 1064,
      "rank_today": 18
    },
    {
      "timestamp": "2025-10-12T08:00:00+02:00",
      "date": "2025-10-12",
      "hour_local": 8,
      "server": "Netherworld",
      "player": "Litus",
      "player_key": "litus",
      "kills_hour": 0,
      "kills_cum_day": 1064,
      "rank_today": 19
    },
    {
      "timestamp": "2025-10-12T09:00:00+02:00",
      "date": "2025-10-12",
      "hour_local": 9,
      "server": "Netherworld",
      "player": "Litus",
      "player_key": "litus",
      "kills_hour": 0,
      "kills_cum_day": 1064,
      "rank_today": 21
    },
    {
      "timestamp": "2025-10-12T10:00:00+02:00",
      "date": "2025-10-12",
      "hour_local": 10,
      "server": "Netherworld",
      "player": "Litus",
      "player_key": "litus",
      "kills_hour": 0,
      "kills_cum_day": 1064,
      "rank_today": 26
    },
    {
      "timestamp": "2025-10-12T01:00:00+02:00",
      "date": "2025-10-12",
      "hour_local": 1,
      "server": "Netherworld",
      "player": "Lunarisa",
      "player_key": "lunarisa",
      "kills_hour": 1533,
      "kills_cum_day": 1533,
      "rank_today": 8
    },
    {
      "timestamp": "2025-10-12T05:00:00+02:00",
      "date": "2025-10-12",
      "hour_local": 5,
      "server": "Netherworld",
      "player": "Lunarisa",
      "player_key": "lunarisa",
      "kills_hour": 6208,
      "kills_cum_day": 7741,
      "rank_today": 4
    },
    {
      "timestamp": "2025-10-12T06:00:00+02:00",
      "date": "2025-10-12",
      "hour_local": 6,
      "server": "Netherworld",
      "player": "Lunarisa",
      "player_key": "lunarisa",
      "kills_hour": 0,
      "kills_cum_day": 7741,
      "rank_today": 4
    },
    {
      "timestamp": "2025-10-12T07:00:00+02:00",
      "date": "2025-10-12",
      "hour_local": 7,
      "server": "Netherworld",
      "player": "Lunarisa",
      "player_key": "lunarisa",
      "kills_hour": 0,
      "kills_cum_day": 7741,
      "rank_today": 4
    },
    {
      "timestamp": "2025-10-12T08:00:00+02:00",
      "date": "2025-10-12",
      "hour_local": 8,
      "server": "Netherworld",
      "player": "Lunarisa",
      "player_key": "lunarisa",
      "kills_hour": 0,
      "kills_cum_day": 7741,
      "rank_today": 5
    },
    {
      "timestamp": "2025-10-12T09:00:00+02:00",
      "date": "2025-10-12",
      "hour_local": 9,
      "server": "Netherworld",
      "player": "Lunarisa",
      "player_key": "lunarisa",
      "kills_hour": 0,
      "kills_cum_day": 7741,
      "rank_today": 6
    },
    {
      "timestamp": "2025-10-12T10:00:00+02:00",
      "date": "2025-10-12",
      "hour_local": 10,
      "server": "Netherworld",
      "player": "Lunarisa",
      "player_key": "lunarisa",
      "kills_hour": 0,
      "kills_cum_day": 7741,
      "rank_today": 6
    },
    {
      "timestamp": "2025-10-12T00:00:00+02:00",
      "date": "2025-10-12",
      "hour_local": 0,
      "server": "Netherworld",
      "player": "marryme",
      "player_key": "marryme",
      "kills_hour": 1756,
      "kills_cum_day": 1756,
      "rank_today": 2
    },
    {
      "timestamp": "2025-10-12T01:00:00+02:00",
      "date": "2025-10-12",
      "hour_local": 1,
      "server": "Netherworld",
      "player": "marryme",
      "player_key": "marryme",
      "kills_hour": 2636,
      "kills_cum_day": 4392,
      "rank_today": 1
    },
    {
      "timestamp": "2025-10-12T05:00:00+02:00",
      "date": "2025-10-12",
      "hour_local": 5,
      "server": "Netherworld",
      "player": "marryme",
      "player_key": "marryme",
      "kills_hour": 11075,
      "kills_cum_day": 15467,
      "rank_today": 1
    },
    {
      "timestamp": "2025-10-12T06:00:00+02:00",
      "date": "2025-10-12",
      "hour_local": 6,
      "server": "Netherworld",
      "player": "marryme",
      "player_key": "marryme",
      "kills_hour": 5444,
      "kills_cum_day": 20911,
      "rank_today": 1
    },
    {
      "timestamp": "2025-10-12T07:00:00+02:00",
      "date": "2025-10-12",
      "hour_local": 7,
      "server": "Netherworld",
      "player": "marryme",
      "player_key": "marryme",
      "kills_hour": 3584,
      "kills_cum_day": 24495,
      "rank_today": 1
    },
    {
      "timestamp": "2025-10-12T08:00:00+02:00",
      "date": "2025-10-12",
      "hour_local": 8,
      "server": "Netherworld",
      "player": "marryme",
      "player_key": "marryme",
      "kills_hour": 3934,
      "kills_cum_day": 28429,
      "rank_today": 1
    },
    {
      "timestamp": "2025-10-12T09:00:00+02:00",
      "date": "2025-10-12",
      "hour_local": 9,
      "server": "Netherworld",
      "player": "marryme",
      "player_key": "marryme",
      "kills_hour": 1302,
      "kills_cum_day": 29731,
      "rank_today": 1
    },
    {
      "timestamp": "2025-10-12T10:00:00+02:00",
      "date": "2025-10-12",
      "hour_local": 10,
      "server": "Netherworld",
      "player": "marryme",
      "player_key": "marryme",
      "kills_hour": 0,
      "kills_cum_day": 29731,
      "rank_today": 1
    },
    {
      "timestamp": "2025-10-12T10:00:00+02:00",
      "date": "2025-10-12",
      "hour_local": 10,
      "server": "Netherworld",
      "player": "Mika",
      "player_key": "mika",
      "kills_hour": 3714,
      "kills_cum_day": 3714,
      "rank_today": 10
    },
    {
      "timestamp": "2025-10-12T05:00:00+02:00",
      "date": "2025-10-12",
      "hour_local": 5,
      "server": "Netherworld",
      "player": "Mizu",
      "player_key": "mizu",
      "kills_hour": 171,
      "kills_cum_day": 171,
      "rank_today": 26
    },
    {
      "timestamp": "2025-10-12T06:00:00+02:00",
      "date": "2025-10-12",
      "hour_local": 6,
      "server": "Netherworld",
      "player": "Mizu",
      "player_key": "mizu",
      "kills_hour": 0,
      "kills_cum_day": 171,
      "rank_today": 28
    },
    {
      "timestamp": "2025-10-12T07:00:00+02:00",
      "date": "2025-10-12",
      "hour_local": 7,
      "server": "Netherworld",
      "player": "Mizu",
      "player_key": "mizu",
      "kills_hour": 0,
      "kills_cum_day": 171,
      "rank_today": 29
    },
    {
      "timestamp": "2025-10-12T08:00:00+02:00",
      "date": "2025-10-12",
      "hour_local": 8,
      "server": "Netherworld",
      "player": "Mizu",
      "player_key": "mizu",
      "kills_hour": 0,
      "kills_cum_day": 171,
      "rank_today": 33
    },
    {
      "timestamp": "2025-10-12T09:00:00+02:00",
      "date": "2025-10-12",
      "hour_local": 9,
      "server": "Netherworld",
      "player": "Mizu",
      "player_key": "mizu",
      "kills_hour": 0,
      "kills_cum_day": 171,
      "rank_today": 36
    },
    {
      "timestamp": "2025-10-12T10:00:00+02:00",
      "date": "2025-10-12",
      "hour_local": 10,
      "server": "Netherworld",
      "player": "Mizu",
      "player_key": "mizu",
      "kills_hour": 0,
      "kills_cum_day": 171,
      "rank_today": 38
    },
    {
      "timestamp": "2025-10-12T00:00:00+02:00",
      "date": "2025-10-12",
      "hour_local": 0,
      "server": "Netherworld",
      "player": "Nalah",
      "player_key": "nalah",
      "kills_hour": 201,
      "kills_cum_day": 201,
      "rank_today": 13
    },
    {
      "timestamp": "2025-10-12T01:00:00+02:00",
      "date": "2025-10-12",
      "hour_local": 1,
      "server": "Netherworld",
      "player": "Nalah",
      "player_key": "nalah",
      "kills_hour": 298,
      "kills_cum_day": 499,
      "rank_today": 14
    },
    {
      "timestamp": "2025-10-12T05:00:00+02:00",
      "date": "2025-10-12",
      "hour_local": 5,
      "server": "Netherworld",
      "player": "Nalah",
      "player_key": "nalah",
      "kills_hour": 527,
      "kills_cum_day": 1026,
      "rank_today": 19
    },
    {
      "timestamp": "2025-10-12T06:00:00+02:00",
      "date": "2025-10-12",
      "hour_local": 6,
      "server": "Netherworld",
      "player": "Nalah",
      "player_key": "nalah",
      "kills_hour": 0,
      "kills_cum_day": 1026,
      "rank_today": 20
    },
    {
      "timestamp": "2025-10-12T07:00:00+02:00",
      "date": "2025-10-12",
      "hour_local": 7,
      "server": "Netherworld",
      "player": "Nalah",
      "player_key": "nalah",
      "kills_hour": 0,
      "kills_cum_day": 1026,
      "rank_today": 20
    },
    {
      "timestamp": "2025-10-12T08:00:00+02:00",
      "date": "2025-10-12",
      "hour_local": 8,
      "server": "Netherworld",
      "player": "Nalah",
      "player_key": "nalah",
      "kills_hour": 0,
      "kills_cum_day": 1026,
      "rank_today": 21
    },
    {
      "timestamp": "2025-10-12T09:00:00+02:00",
      "date": "2025-10-12",
      "hour_local": 9,
      "server": "Netherworld",
      "player": "Nalah",
      "player_key": "nalah",
      "kills_hour": 0,
      "kills_cum_day": 1026,
      "rank_today": 23
    },
    {
      "timestamp": "2025-10-12T10:00:00+02:00",
      "date": "2025-10-12",
      "hour_local": 10,
      "server": "Netherworld",
      "player": "Nalah",
      "player_key": "nalah",
      "kills_hour": 0,
      "kills_cum_day": 1026,
      "rank_today": 28
    },
    {
      "timestamp": "2025-10-12T09:00:00+02:00",
      "date": "2025-10-12",
      "hour_local": 9,
      "server": "Netherworld",
      "player": "OgGacek",
      "player_key": "oggacek",
      "kills_hour": 422,
      "kills_cum_day": 422,
      "rank_today": 32
    },
    {
      "timestamp": "2025-10-12T10:00:00+02:00",
      "date": "2025-10-12",
      "hour_local": 10,
      "server": "Netherworld",
      "player": "OgGacek",
      "player_key": "oggacek",
      "kills_hour": 3770,
      "kills_cum_day": 4192,
      "rank_today": 9
    },
    {
      "timestamp": "2025-10-12T10:00:00+02:00",
      "date": "2025-10-12",
      "hour_local": 10,
      "server": "Netherworld",
      "player": "Phantoms",
      "player_key": "phantoms",
      "kills_hour": 3477,
      "kills_cum_day": 3477,
      "rank_today": 11
    },
    {
      "timestamp": "2025-10-12T10:00:00+02:00",
      "date": "2025-10-12",
      "hour_local": 10,
      "server": "Netherworld",
      "player": "Quake",
      "player_key": "quake",
      "kills_hour": 31,
      "kills_cum_day": 31,
      "rank_today": 42
    },
    {
      "timestamp": "2025-10-12T05:00:00+02:00",
      "date": "2025-10-12",
      "hour_local": 5,
      "server": "Netherworld",
      "player": "Ralf",
      "player_key": "ralf",
      "kills_hour": 145,
      "kills_cum_day": 145,
      "rank_today": 27
    },
    {
      "timestamp": "2025-10-12T06:00:00+02:00",
      "date": "2025-10-12",
      "hour_local": 6,
      "server": "Netherworld",
      "player": "Ralf",
      "player_key": "ralf",
      "kills_hour": 0,
      "kills_cum_day": 145,
      "rank_today": 29
    },
    {
      "timestamp": "2025-10-12T07:00:00+02:00",
      "date": "2025-10-12",
      "hour_local": 7,
      "server": "Netherworld",
      "player": "Ralf",
      "player_key": "ralf",
      "kills_hour": 631,
      "kills_cum_day": 776,
      "rank_today": 24
    },
    {
      "timestamp": "2025-10-12T08:00:00+02:00",
      "date": "2025-10-12",
      "hour_local": 8,
      "server": "Netherworld",
      "player": "Ralf",
      "player_key": "ralf",
      "kills_hour": 154,
      "kills_cum_day": 930,
      "rank_today": 22
    },
    {
      "timestamp": "2025-10-12T09:00:00+02:00",
      "date": "2025-10-12",
      "hour_local": 9,
      "server": "Netherworld",
      "player": "Ralf",
      "player_key": "ralf",
      "kills_hour": 0,
      "kills_cum_day": 930,
      "rank_today": 24
    },
    {
      "timestamp": "2025-10-12T10:00:00+02:00",
      "date": "2025-10-12",
      "hour_local": 10,
      "server": "Netherworld",
      "player": "Ralf",
      "player_key": "ralf",
      "kills_hour": 0,
      "kills_cum_day": 930,
      "rank_today": 29
    },
    {
      "timestamp": "2025-10-12T05:00:00+02:00",
      "date": "2025-10-12",
      "hour_local": 5,
      "server": "Netherworld",
      "player": "Sagoyo",
      "player_key": "sagoyo",
      "kills_hour": 62,
      "kills_cum_day": 62,
      "rank_today": 28
    },
    {
      "timestamp": "2025-10-12T06:00:00+02:00",
      "date": "2025-10-12",
      "hour_local": 6,
      "server": "Netherworld",
      "player": "Sagoyo",
      "player_key": "sagoyo",
      "kills_hour": 11,
      "kills_cum_day": 73,
      "rank_today": 30
    },
    {
      "timestamp": "2025-10-12T07:00:00+02:00",
      "date": "2025-10-12",
      "hour_local": 7,
      "server": "Netherworld",
      "player": "Sagoyo",
      "player_key": "sagoyo",
      "kills_hour": 78,
      "kills_cum_day": 151,
      "rank_today": 30
    },
    {
      "timestamp": "2025-10-12T08:00:00+02:00",
      "date": "2025-10-12",
      "hour_local": 8,
      "server": "Netherworld",
      "player": "Sagoyo",
      "player_key": "sagoyo",
      "kills_hour": 0,
      "kills_cum_day": 151,
      "rank_today": 34
    },
    {
      "timestamp": "2025-10-12T09:00:00+02:00",
      "date": "2025-10-12",
      "hour_local": 9,
      "server": "Netherworld",
      "player": "Sagoyo",
      "player_key": "sagoyo",
      "kills_hour": 1,
      "kills_cum_day": 152,
      "rank_today": 37
    },
    {
      "timestamp": "2025-10-12T10:00:00+02:00",
      "date": "2025-10-12",
      "hour_local": 10,
      "server": "Netherworld",
      "player": "Sagoyo",
      "player_key": "sagoyo",
      "kills_hour": 9,
      "kills_cum_day": 161,
      "rank_today": 39
    },
    {
      "timestamp": "2025-10-12T08:00:00+02:00",
      "date": "2025-10-12",
      "hour_local": 8,
      "server": "Netherworld",
      "player": "temuemployee",
      "player_key": "temuemployee",
      "kills_hour": 130,
      "kills_cum_day": 130,
      "rank_today": 35
    },
    {
      "timestamp": "2025-10-12T09:00:00+02:00",
      "date": "2025-10-12",
      "hour_local": 9,
      "server": "Netherworld",
      "player": "temuemployee",
      "player_key": "temuemployee",
      "kills_hour": 724,
      "kills_cum_day": 854,
      "rank_today": 26
    },
    {
      "timestamp": "2025-10-12T10:00:00+02:00",
      "date": "2025-10-12",
      "hour_local": 10,
      "server": "Netherworld",
      "player": "temuemployee",
      "player_key": "temuemployee",
      "kills_hour": 656,
      "kills_cum_day": 1510,
      "rank_today": 22
    },
    {
      "timestamp": "2025-10-12T00:00:00+02:00",
      "date": "2025-10-12",
      "hour_local": 0,
      "server": "Netherworld",
      "player": "Thaito",
      "player_key": "thaito",
      "kills_hour": 467,
      "kills_cum_day": 467,
      "rank_today": 7
    },
    {
      "timestamp": "2025-10-12T01:00:00+02:00",
      "date": "2025-10-12",
      "hour_local": 1,
      "server": "Netherworld",
      "player": "Thaito",
      "player_key": "thaito",
      "kills_hour": 3580,
      "kills_cum_day": 4047,
      "rank_today": 2
    },
    {
      "timestamp": "2025-10-12T05:00:00+02:00",
      "date": "2025-10-12",
      "hour_local": 5,
      "server": "Netherworld",
      "player": "Thaito",
      "player_key": "thaito",
      "kills_hour": 4209,
      "kills_cum_day": 8256,
      "rank_today": 2
    },
    {
      "timestamp": "2025-10-12T06:00:00+02:00",
      "date": "2025-10-12",
      "hour_local": 6,
      "server": "Netherworld",
      "player": "Thaito",
      "player_key": "thaito",
      "kills_hour": 0,
      "kills_cum_day": 8256,
      "rank_today": 2
    },
    {
      "timestamp": "2025-10-12T07:00:00+02:00",
      "date": "2025-10-12",
      "hour_local": 7,
      "server": "Netherworld",
      "player": "Thaito",
      "player_key": "thaito",
      "kills_hour": 0,
      "kills_cum_day": 8256,
      "rank_today": 2
    },
    {
      "timestamp": "2025-10-12T08:00:00+02:00",
      "date": "2025-10-12",
      "hour_local": 8,
      "server": "Netherworld",
      "player": "Thaito",
      "player_key": "thaito",
      "kills_hour": 0,
      "kills_cum_day": 8256,
      "rank_today": 3
    },
    {
      "timestamp": "2025-10-12T09:00:00+02:00",
      "date": "2025-10-12",
      "hour_local": 9,
      "server": "Netherworld",
      "player": "Thaito",
      "player_key": "thaito",
      "kills_hour": 0,
      "kills_cum_day": 8256,
      "rank_today": 4
    },
    {
      "timestamp": "2025-10-12T10:00:00+02:00",
      "date": "2025-10-12",
      "hour_local": 10,
      "server": "Netherworld",
      "player": "Thaito",
      "player_key": "thaito",
      "kills_hour": 0,
      "kills_cum_day": 8256,
      "rank_today": 5
    },
    {
      "timestamp": "2025-10-12T00:00:00+02:00",
      "date": "2025-10-12",
      "hour_local": 0,
      "server": "Netherworld",
      "player": "TheFool",
      "player_key": "thefool",
      "kills_hour": 354,
      "kills_cum_day": 354,
      "rank_today": 9
    },
    {
      "timestamp": "2025-10-12T01:00:00+02:00",
      "date": "2025-10-12",
      "hour_local": 1,
      "server": "Netherworld",
      "player": "TheFool",
      "player_key": "thefool",
      "kills_hour": 1002,
      "kills_cum_day": 1356,
      "rank_today": 10
    },
    {
      "timestamp": "2025-10-12T05:00:00+02:00",
      "date": "2025-10-12",
      "hour_local": 5,
      "server": "Netherworld",
      "player": "TheFool",
      "player_key": "thefool",
      "kills_hour": 0,
      "kills_cum_day": 1356,
      "rank_today": 15
    },
    {
      "timestamp": "2025-10-12T06:00:00+02:00",
      "date": "2025-10-12",
      "hour_local": 6,
      "server": "Netherworld",
      "player": "TheFool",
      "player_key": "thefool",
      "kills_hour": 0,
      "kills_cum_day": 1356,
      "rank_today": 16
    },
    {
      "timestamp": "2025-10-12T07:00:00+02:00",
      "date": "2025-10-12",
      "hour_local": 7,
      "server": "Netherworld",
      "player": "TheFool",
      "player_key": "thefool",
      "kills_hour": 0,
      "kills_cum_day": 1356,
      "rank_today": 16
    },
    {
      "timestamp": "2025-10-12T08:00:00+02:00",
      "date": "2025-10-12",
      "hour_local": 8,
      "server": "Netherworld",
      "player": "TheFool",
      "player_key": "thefool",
      "kills_hour": 0,
      "kills_cum_day": 1356,
      "rank_today": 18
    },
    {
      "timestamp": "2025-10-12T09:00:00+02:00",
      "date": "2025-10-12",
      "hour_local": 9,
      "server": "Netherworld",
      "player": "TheFool",
      "player_key": "thefool",
      "kills_hour": 0,
      "kills_cum_day": 1356,
      "rank_today": 18
    },
    {
      "timestamp": "2025-10-12T10:00:00+02:00",
      "date": "2025-10-12",
      "hour_local": 10,
      "server": "Netherworld",
      "player": "TheFool",
      "player_key": "thefool",
      "kills_hour": 0,
      "kills_cum_day": 1356,
      "rank_today": 24
    },
    {
      "timestamp": "2025-10-12T00:00:00+02:00",
      "date": "2025-10-12",
      "hour_local": 0,
      "server": "Netherworld",
      "player": "WannaHaveItAll",
      "player_key": "wannahaveitall",
      "kills_hour": 47,
      "kills_cum_day": 47,
      "rank_today": 14
    },
    {
      "timestamp": "2025-10-12T01:00:00+02:00",
      "date": "2025-10-12",
      "hour_local": 1,
      "server": "Netherworld",
      "player": "WannaHaveItAll",
      "player_key": "wannahaveitall",
      "kills_hour": 0,
      "kills_cum_day": 47,
      "rank_today": 18
    },
    {
      "timestamp": "2025-10-12T05:00:00+02:00",
      "date": "2025-10-12",
      "hour_local": 5,
      "server": "Netherworld",
      "player": "WannaHaveItAll",
      "player_key": "wannahaveitall",
      "kills_hour": 0,
      "kills_cum_day": 47,
      "rank_today": 30
    },
    {
      "timestamp": "2025-10-12T06:00:00+02:00",
      "date": "2025-10-12",
      "hour_local": 6,
      "server": "Netherworld",
      "player": "WannaHaveItAll",
      "player_key": "wannahaveitall",
      "kills_hour": 0,
      "kills_cum_day": 47,
      "rank_today": 31
    },
    {
      "timestamp": "2025-10-12T07:00:00+02:00",
      "date": "2025-10-12",
      "hour_local": 7,
      "server": "Netherworld",
      "player": "WannaHaveItAll",
      "player_key": "wannahaveitall",
      "kills_hour": 0,
      "kills_cum_day": 47,
      "rank_today": 31
    },
    {
      "timestamp": "2025-10-12T08:00:00+02:00",
      "date": "2025-10-12",
      "hour_local": 8,
      "server": "Netherworld",
      "player": "WannaHaveItAll",
      "player_key": "wannahaveitall",
      "kills_hour": 0,
      "kills_cum_day": 47,
      "rank_today": 36
    },
    {
      "timestamp": "2025-10-12T09:00:00+02:00",
      "date": "2025-10-12",
      "hour_local": 9,
      "server": "Netherworld",
      "player": "WannaHaveItAll",
      "player_key": "wannahaveitall",
      "kills_hour": 0,
      "kills_cum_day": 47,
      "rank_today": 38
    },
    {
      "timestamp": "2025-10-12T10:00:00+02:00",
      "date": "2025-10-12",
      "hour_local": 10,
      "server": "Netherworld",
      "player": "WannaHaveItAll",
      "player_key": "wannahaveitall",
      "kills_hour": 0,
      "kills_cum_day": 47,
      "rank_today": 41
    },
    {
      "timestamp": "2025-10-12T00:00:00+02:00",
      "date": "2025-10-12",
      "hour_local": 0,
      "server": "Netherworld",
      "player": "Wodjin",
      "player_key": "wodjin",
      "kills_hour": 283,
      "kills_cum_day": 283,
      "rank_today": 10
    },
    {
      "timestamp": "2025-10-12T01:00:00+02:00",
      "date": "2025-10-12",
      "hour_local": 1,
      "server": "Netherworld",
      "player": "Wodjin",
      "player_key": "wodjin",
      "kills_hour": 0,
      "kills_cum_day": 283,
      "rank_today": 16
    },
    {
      "timestamp": "2025-10-12T05:00:00+02:00",
      "date": "2025-10-12",
      "hour_local": 5,
      "server": "Netherworld",
      "player": "Wodjin",
      "player_key": "wodjin",
      "kills_hour": 0,
      "kills_cum_day": 283,
      "rank_today": 25
    },
    {
      "timestamp": "2025-10-12T06:00:00+02:00",
      "date": "2025-10-12",
      "hour_local": 6,
      "server": "Netherworld",
      "player": "Wodjin",
      "player_key": "wodjin",
      "kills_hour": 0,
      "kills_cum_day": 283,
      "rank_today": 27
    },
    {
      "timestamp": "2025-10-12T07:00:00+02:00",
      "date": "2025-10-12",
      "hour_local": 7,
      "server": "Netherworld",
      "player": "Wodjin",
      "player_key": "wodjin",
      "kills_hour": 0,
      "kills_cum_day": 283,
      "rank_today": 28
    },
    {
      "timestamp": "2025-10-12T08:00:00+02:00",
      "date": "2025-10-12",
      "hour_local": 8,
      "server": "Netherworld",
      "player": "Wodjin",
      "player_key": "wodjin",
      "kills_hour": 0,
      "kills_cum_day": 283,
      "rank_today": 31
    },
    {
      "timestamp": "2025-10-12T09:00:00+02:00",
      "date": "2025-10-12",
      "hour_local": 9,
      "server": "Netherworld",
      "player": "Wodjin",
      "player_key": "wodjin",
      "kills_hour": 0,
      "kills_cum_day": 283,
      "rank_today": 34
    },
    {
      "timestamp": "2025-10-12T10:00:00+02:00",
      "date": "2025-10-12",
      "hour_local": 10,
      "server": "Netherworld",
      "player": "Wodjin",
      "player_key": "wodjin",
      "kills_hour": 0,
      "kills_cum_day": 283,
      "rank_today": 37
    },
    {
      "timestamp": "2025-10-12T00:00:00+02:00",
      "date": "2025-10-12",
      "hour_local": 0,
      "server": "Netherworld",
      "player": "Yoshimitsu",
      "player_key": "yoshimitsu",
      "kills_hour": 432,
      "kills_cum_day": 432,
      "rank_today": 8
    },
    {
      "timestamp": "2025-10-12T01:00:00+02:00",
      "date": "2025-10-12",
      "hour_local": 1,
      "server": "Netherworld",
      "player": "Yoshimitsu",
      "player_key": "yoshimitsu",
      "kills_hour": 656,
      "kills_cum_day": 1088,
      "rank_today": 11
    },
    {
      "timestamp": "2025-10-12T05:00:00+02:00",
      "date": "2025-10-12",
      "hour_local": 5,
      "server": "Netherworld",
      "player": "Yoshimitsu",
      "player_key": "yoshimitsu",
      "kills_hour": 0,
      "kills_cum_day": 1088,
      "rank_today": 16
    },
    {
      "timestamp": "2025-10-12T06:00:00+02:00",
      "date": "2025-10-12",
      "hour_local": 6,
      "server": "Netherworld",
      "player": "Yoshimitsu",
      "player_key": "yoshimitsu",
      "kills_hour": 0,
      "kills_cum_day": 1088,
      "rank_today": 17
    },
    {
      "timestamp": "2025-10-12T07:00:00+02:00",
      "date": "2025-10-12",
      "hour_local": 7,
      "server": "Netherworld",
      "player": "Yoshimitsu",
      "player_key": "yoshimitsu",
      "kills_hour": 123,
      "kills_cum_day": 1211,
      "rank_today": 17
    },
    {
      "timestamp": "2025-10-12T08:00:00+02:00",
      "date": "2025-10-12",
      "hour_local": 8,
      "server": "Netherworld",
      "player": "Yoshimitsu",
      "player_key": "yoshimitsu",
      "kills_hour": 276,
      "kills_cum_day": 1487,
      "rank_today": 16
    },
    {
      "timestamp": "2025-10-12T09:00:00+02:00",
      "date": "2025-10-12",
      "hour_local": 9,
      "server": "Netherworld",
      "player": "Yoshimitsu",
      "player_key": "yoshimitsu",
      "kills_hour": 128,
      "kills_cum_day": 1615,
      "rank_today": 15
    },
    {
      "timestamp": "2025-10-12T10:00:00+02:00",
      "date": "2025-10-12",
      "hour_local": 10,
      "server": "Netherworld",
      "player": "Yoshimitsu",
      "player_key": "yoshimitsu",
      "kills_hour": 287,
      "kills_cum_day": 1902,
      "rank_today": 19
    },
    {
      "timestamp": "2025-10-12T00:00:00+02:00",
      "date": "2025-10-12",
      "hour_local": 0,
      "server": "Netherworld",
      "player": "Zoey",
      "player_key": "zoey",
      "kills_hour": 1040,
      "kills_cum_day": 1040,
      "rank_today": 5
    },
    {
      "timestamp": "2025-10-12T01:00:00+02:00",
      "date": "2025-10-12",
      "hour_local": 1,
      "server": "Netherworld",
      "player": "Zoey",
      "player_key": "zoey",
      "kills_hour": 2052,
      "kills_cum_day": 3092,
      "rank_today": 6
    },
    {
      "timestamp": "2025-10-12T05:00:00+02:00",
      "date": "2025-10-12",
      "hour_local": 5,
      "server": "Netherworld",
      "player": "Zoey",
      "player_key": "zoey",
      "kills_hour": 2682,
      "kills_cum_day": 5774,
      "rank_today": 5
    },
    {
      "timestamp": "2025-10-12T06:00:00+02:00",
      "date": "2025-10-12",
      "hour_local": 6,
      "server": "Netherworld",
      "player": "Zoey",
      "player_key": "zoey",
      "kills_hour": 0,
      "kills_cum_day": 5774,
      "rank_today": 5
    },
    {
      "timestamp": "2025-10-12T07:00:00+02:00",
      "date": "2025-10-12",
      "hour_local": 7,
      "server": "Netherworld",
      "player": "Zoey",
      "player_key": "zoey",
      "kills_hour": 0,
      "kills_cum_day": 5774,
      "rank_today": 5
    },
    {
      "timestamp": "2025-10-12T08:00:00+02:00",
      "date": "2025-10-12",
      "hour_local": 8,
      "server": "Netherworld",
      "player": "Zoey",
      "player_key": "zoey",
      "kills_hour": 0,
      "kills_cum_day": 5774,
      "rank_today": 6
    },
    {
      "timestamp": "2025-10-12T09:00:00+02:00",
      "date": "2025-10-12",
      "hour_local": 9,
      "server": "Netherworld",
      "player": "Zoey",
      "player_key": "zoey",
      "kills_hour": 0,
      "kills_cum_day": 5774,
      "rank_today": 8
    },
    {
      "timestamp": "2025-10-12T10:00:00+02:00",
      "date": "2025-10-12",
      "hour_local": 10,
      "server": "Netherworld",
      "player": "Zoey",
      "player_key": "zoey",
      "kills_hour": 0,
      "kills_cum_day": 5774,
      "rank_today": 8
    }
  ]
}